tests/__init__.py
tests/test_youtube_wrapper.py
youtube_wrapper/__init__.py
youtube_wrapper/data_api.py
youtube_wrapper/transcript_api.py
youtube_wrapper_nav-0.1.0.dist-info/LICENSE
youtube_wrapper_nav-0.1.0.dist-info/METADATA
youtube_wrapper_nav-0.1.0.dist-info/WHEEL
youtube_wrapper_nav-0.1.0.dist-info/top_level.txt
youtube_wrapper_nav-0.1.0.dist-info/RECORD
