Metadata-Version: 2.1
Name: youtube-wrapper-nav
Version: 0.1.0
Summary: A Python wrapper for YouTube Data API and YouTube Transcript API
Home-page: https://github.com/navroop-ch/youtube_wrapper
Author: Navroop Chandwani
Author-email: navroopchandwani@gmail.com
Classifier: Programming Language :: Python :: 3
Classifier: License :: OSI Approved :: MIT License
Classifier: Operating System :: OS Independent
Requires-Python: >=3.6
License-File: LICENSE
Requires-Dist: google-api-python-client
Requires-Dist: youtube-transcript-api
